serializeme/__init__.py
serializeme/deserialize.py
serializeme/ex.py
serializeme/exceptions.py
serializeme/field.py
serializeme/main.py
serializeme/serialize.py
serializeme-0.0.26.dist-info/LICENSE
serializeme-0.0.26.dist-info/METADATA
serializeme-0.0.26.dist-info/WHEEL
serializeme-0.0.26.dist-info/top_level.txt
serializeme-0.0.26.dist-info/RECORD
