Metadata-Version: 2.1
Name: serializeme
Version: 0.0.26
Summary: Python package meant to serialize/deserialize network packets.
Home-page: UNKNOWN
Author: Jack Gisel, Justin Roosenschoon, Thai Truong
License: UNKNOWN
Keywords: python,network,packet,serialize,networking
Platform: UNKNOWN
Classifier: Development Status :: 3 - Alpha
Classifier: Intended Audience :: Education
Classifier: Programming Language :: Python :: 3
Classifier: Operating System :: MacOS :: MacOS X
Classifier: Operating System :: Microsoft :: Windows
License-File: LICENSE
